<collection xmlns="http://exist.sourceforge.net/NS/exist" name="/db/apps/clarin/views" owner="admin" group="dba" mode="755" created="2012-12-11T11:42:33+01:00" deduplicate-blobs="false" version="2">
    <acl entries="0" version="1"/>
    <resource type="BinaryResource" name="list-sbs.xq" owner="admin" group="dba" mode="755" created="2012-12-12T16:37:58+01:00" modified="2014-04-29T18:39:31+02:00" filename="list-sbs.xq" mimetype="application/xquery" blob-id="d97b89d7cbc47611218512dc6a6d9a5037b6c3179bfc4fbed1af626fd8574d54">
        <acl entries="0" version="1"/>
    </resource>
    <resource type="BinaryResource" name="view-sb.xq" owner="admin" group="dba" mode="755" created="2012-12-12T17:09:07+01:00" modified="2014-10-23T15:06:36+02:00" filename="view-sb.xq" mimetype="application/xquery" blob-id="ac64b75c3fc81e790ff5970734eaaf09ea0cd6d5fdae69d0636d4340743ff931">
        <acl entries="0" version="1"/>
    </resource>
    <resource type="BinaryResource" name="recommendation.xq" owner="admin" group="dba" mode="755" created="2014-12-22T17:07:47+01:00" modified="2014-12-23T14:53:03+01:00" filename="recommendation.xq" mimetype="application/xquery" blob-id="e9652b04e09192e2b06f34b8c0eaf7f26931b1d3b3fc82724f9d9c16031a06df">
        <acl entries="0" version="1"/>
    </resource>
    <resource type="BinaryResource" name="add-spec-version.xq" owner="admin" group="dba" mode="755" created="2013-03-12T12:21:24+01:00" modified="2014-05-16T16:14:21+02:00" filename="add-spec-version.xq" mimetype="application/xquery" blob-id="83639777d984576350c0dca57111a8a68921d78ed5d82d7f1d3d06163a0e4b45">
        <acl entries="0" version="1"/>
    </resource>
    <resource type="BinaryResource" name="register-confirmation.xq" owner="admin" group="dba" mode="745" created="2014-05-16T13:54:36+02:00" modified="2014-05-16T13:54:36+02:00" filename="register-confirmation.xq" mimetype="application/xquery" blob-id="c1f80094f0030c055fefe478d96fe130b7c7f03756b11a6360b7a8bccd1e16d4">
        <acl entries="0" version="1"/>
    </resource>
    <resource type="BinaryResource" name="list-specs.xq" owner="admin" group="dba" mode="755" created="2012-12-12T13:24:43+01:00" modified="2015-01-20T17:23:50+01:00" filename="list-specs.xq" mimetype="application/xquery" blob-id="ed231730b38499194fdbc24488178fd3a918096357827eb53463ade179ee0b57">
        <acl entries="0" version="1"/>
    </resource>
    <resource type="BinaryResource" name="register-spec.xq" owner="admin" group="dba" mode="755" created="2013-03-18T17:08:04+01:00" modified="2021-01-29T18:20:23+01:00" filename="register-spec.xq" mimetype="application/xquery" blob-id="6940ac79f88e79476f7a43f784d9e50d41a4e9ed3b7eee6e12019cf51a97dbb2">
        <acl entries="0" version="1"/>
    </resource>
    <resource type="BinaryResource" name="register-version.xq" owner="admin" group="dba" mode="755" created="2013-03-19T15:34:02+01:00" modified="2021-01-29T18:31:08+01:00" filename="register-version.xq" mimetype="application/xquery" blob-id="25e4c22de602075acd9802cf3f729abccd4329a53d30c857aaeaf498d0c7e937">
        <acl entries="0" version="1"/>
    </resource>
    <resource type="BinaryResource" name="register-part.xq" owner="admin" group="dba" mode="755" created="2013-03-19T14:50:06+01:00" modified="2021-01-29T18:33:26+01:00" filename="register-part.xq" mimetype="application/xquery" blob-id="a82abe04a003fdf5ce7b849084a59763fe1822bea6a409711f227aaf6fea0d0f">
        <acl entries="0" version="1"/>
    </resource>
    <resource type="BinaryResource" name="list-topics.xq" owner="admin" group="dba" mode="755" created="2012-12-12T11:39:31+01:00" modified="2013-12-04T17:28:44+01:00" filename="list-topics.xq" mimetype="application/xquery" blob-id="bc6089d72d02500b0659be76fde3aec18a2f7ddecf3bc0bf16f2299f4b7f6995">
        <acl entries="0" version="1"/>
    </resource>
    <resource type="BinaryResource" name="view-spec.xq" owner="admin" group="dba" mode="755" created="2012-12-12T13:24:31+01:00" modified="2014-12-22T17:05:42+01:00" filename="view-spec.xq" mimetype="application/xquery" blob-id="bc75b3b6499c5fcc5cb7fe035b0ee2c3a8febafdb18ecc301fa4c85925dc5a6b">
        <acl entries="0" version="1"/>
    </resource>
    <resource type="BinaryResource" name="add-spec-part.xq" owner="admin" group="dba" mode="755" created="2013-03-15T09:47:57+01:00" modified="2014-05-16T16:14:06+02:00" filename="add-spec-part.xq" mimetype="application/xquery" blob-id="04f1c14aea325ef6f3af7437f558365ce58a2efaa30001045e90690aad7e6fa6">
        <acl entries="0" version="1"/>
    </resource>
    <resource type="BinaryResource" name="contact.xq" owner="admin" group="dba" mode="755" created="2012-12-12T15:59:28+01:00" modified="2014-08-27T16:06:36+02:00" filename="contact.xq" mimetype="application/xquery" blob-id="8d97e9c062875b757dbfaa532985955bc9e17cb6b65783882bed1b114e2802c2">
        <acl entries="0" version="1"/>
    </resource>
    <resource type="BinaryResource" name="view-topic.xq" owner="admin" group="dba" mode="755" created="2012-12-12T12:44:59+01:00" modified="2014-10-23T15:07:00+02:00" filename="view-topic.xq" mimetype="application/xquery" blob-id="d0250cddc7948d9738962f86ca9295cb9d3291e1fbf6820fe9e14f3a3b34c465">
        <acl entries="0" version="1"/>
    </resource>
    <resource type="BinaryResource" name="untitled.xquery" owner="admin" group="dba" mode="644" created="2021-01-14T15:11:06+01:00" modified="2021-01-14T15:43:21+01:00" filename="untitled.xquery" mimetype="application/xquery" blob-id="8529a1f73e00f82cc3e043dcef6452c547c752c22320a2fae5d99ff4c2250835">
        <acl entries="0" version="1"/>
    </resource>
</collection>