<spec xmlns:xsi="http://www.w3.org/2001/XMLSchema-instance" id="SpecOpenCyc" standardSettingBody="SBOther" topic="TopicOntology" xsi:noNamespaceSchemaLocation="../../schemas/spec.xsd"><titleStmt><title>OpenCyc</title><abbr>OpenCyc</abbr></titleStmt><scope>Upper level ontology</scope><info type="description"><p>OpenCyc is the open source version of the Cyc technology, that is an ontology containing 
            hundreds of thousands of Cyc terms covering all human consensus reality domains. It is 
            available for download under an OpenCyc License. Release 4.0 of OpenCyc includes:</p><ul><li>~239,000 terms</li><li>~2,093,000 triples</li><li>Select class (direct and indirect) instance counts</li><li>~69,000 owl:sameAs links to external (non-Cyc) semantic data namespaces</li><li>English strings (a canonical one and alternatives) corresponding to each concept term, to assist with search and display.</li><li> A java-based Cyc Inference Engine and the Cyc Knowledge Base Browser.</li><li> Documentation and self-paced learning materials to help users achieve a basic- to
            intermediate-level understanding of the issues of knowledge representation and application
            development using Cyc</li><li> A specification of CycL, the language in which Cyc (and hence OpenCyc) is written. There
            are CycL-to-Lisp, CycL-to-C, etc. translators.</li><li> A specification of the Cyc API, by calling which a programmer can build an OpenCyc
                application with very little familiarity with CycL or with the OpenCyc KB. </li></ul></info><relation target="SpecUmbel" type="isUsedBy"/><version id="SpecOpenCyc-4.0"><titleStmt><abbr internal="yes">OpenCyc 4.0</abbr><respStmt><resp>Author</resp><name>Cycorp</name></respStmt></titleStmt><versionNumber type="minor">4.0</versionNumber><date>2012</date><address type="URL">http://www.cyc.com/platform/opencyc/</address></version></spec>