<?xml-model href="../../schemas/format.xsd" type="application/xml" schematypens="http://purl.oclc.org/dsdl/schematron"?>
<format xmlns:xsi="http://www.w3.org/2001/XMLSchema-instance" id="fGrAF" xsi:noNamespaceSchemaLocation="../../schemas/format.xsd" display="show">
  <titleStmt>
    <title>Graph  Annotation  Format</title>
    <abbr>GrAF</abbr>
  </titleStmt>
  <keyword>annotation format</keyword>  
  <info type="description">
    <p>The 
      <a href="https://www.cs.vassar.edu/~ide/papers/LAW.pdf">GrAF</a> is  an  XML serialization  of  the  <a href="../views/view-spec.xq?id=SpecLaf">Linguistic  Annotation  Format (LAF)</a> developed within ISO TC37 SC4.</p>
  </info>
  <relation target="SpecLaf" type="isDefinedBy"/>
  <mimeType>application/xml</mimeType>
  <fileExt>.xml</fileExt>
  <formatFamily>XML</formatFamily>
</format>
